llm_fragments_pure.py
llm_fragments_pure-0.2.dist-info/licenses/LICENSE
llm_fragments_pure-0.2.dist-info/METADATA
llm_fragments_pure-0.2.dist-info/WHEEL
llm_fragments_pure-0.2.dist-info/entry_points.txt
llm_fragments_pure-0.2.dist-info/top_level.txt
llm_fragments_pure-0.2.dist-info/RECORD
