Metadata-Version: 2.4
Name: llm-fragments-pure
Version: 0.2
Summary: Run URLs through the pure.md API
Author: Assistant
License-Expression: Apache-2.0
Project-URL: Homepage, https://github.com/user/llm-fragments-pure
Requires-Python: >=3.9
License-File: LICENSE
Requires-Dist: llm
Requires-Dist: httpx
Provides-Extra: test
Requires-Dist: pytest; extra == "test"
Requires-Dist: pytest-httpx; extra == "test"
Dynamic: license-file
